candyshop/__init__.py
candyshop/bundle.py
candyshop/environment.py
candyshop/utils.py
candyshop-0.2.2.dist-info/AUTHORS.rst
candyshop-0.2.2.dist-info/LICENSE
candyshop-0.2.2.dist-info/METADATA
candyshop-0.2.2.dist-info/WHEEL
candyshop-0.2.2.dist-info/top_level.txt
candyshop-0.2.2.dist-info/RECORD
