Metadata-Version: 2.1
Name: candyshop
Version: 0.2.2
Summary: Candyshop is a helper to determine if all your dependencies are declared properly.
Home-page: https://github.com/LuisAlejandro/candyshop
Author: Luis Alejandro Martínez Faneyth
Author-email: luis@collagelabs.org
License: GNU GENERAL PUBLIC LICENSE
Keywords: odoo,requirements
Platform: posix
Platform: linux
Classifier: Development Status :: 5 - Production/Stable
Classifier: Intended Audience :: Developers
Classifier: License :: OSI Approved :: GNU General Public License v3 (GPLv3)
Classifier: Natural Language :: English
Classifier: Programming Language :: Python :: 3
Classifier: Programming Language :: Python :: 3.8
Classifier: Programming Language :: Python :: 3.9
Classifier: Programming Language :: Python :: 3.10
Classifier: Programming Language :: Python :: 3.11
License-File: LICENSE
License-File: AUTHORS.rst
Requires-Dist: sh (==1.14.2)
Requires-Dist: lxml (==4.8.0)
